{"stats":{"minecraft:dropped":{"minecraft:smooth_sandstone":1},"minecraft:used":{"minecraft:stone_bricks":644,"minecraft:dark_oak_planks":111,"minecraft:stone_stairs":1,"minecraft:stone_brick_slab":29,"minecraft:spruce_planks":162,"minecraft:stone":523,"minecraft:smooth_stone":28,"minecraft:stone_brick_stairs":14},"minecraft:custom":{"minecraft:jump":38,"minecraft:time_since_rest":92145,"minecraft:sprint_one_cm":417,"minecraft:crouch_one_cm":474,"minecraft:leave_game":2,"minecraft:play_time":92145,"minecraft:time_since_death":92145,"minecraft:walk_one_cm":10631,"minecraft:sneak_time":7501,"minecraft:total_world_time":93473,"minecraft:drop":1,"minecraft:fly_one_cm":746365}},"DataVersion":3105}